Workbook

Sheet Read Me
A1: Stockstrail SEO / AEO / GEO blueprint
A2: Prepared 9 Oct 2026 from a live read of stockstrail.in plus current search data.
A5: WHAT'S IN THIS FILE
A6: Meta - Main Site | B6: 49 pages of stockstrail.in: new title + description, keywords, intent, priority, indexing and implementation notes, next to your current values.
A7: Meta - Learning | B7: 52 pages of learning.stockstrail.in (hub, categories, courses, lessons).
A8: Keyword Map | B8: 41 target keywords mapped to pages, with estimated demand / competition and the realistic winnability.
A9: Fix List | B9: 24 technical, content and compliance issues found on the live site, prioritised.
A10: AEO-GEO Playbook | B10: 13 levers for being cited in AI Overviews, AI Mode and other AI answers.
A12: RULES USED FOR EVERY TITLE AND DESCRIPTION
A13: Brand | B13: 'Stockstrail' appears in every title. Home leads with the brand; other pages lead with the keyword and close with '| Stockstrail'.
A14: Title length | B14: 60 characters or fewer so most are not cut off. Google has no fixed limit; truncation depends on pixel width.
A15: Description length | B15: About 125-160 characters with the key point in the first ~120. Google states there is no length limit and truncates to fit the device width; it only sometimes uses your description, and descriptions are not a ranking factor. Their job is clarity and click-through.
A16: Claims | B16: No 'best', 'top', 'guaranteed', 'unbiased', 'zero commission' or unverifiable numbers. Rates, tax and holiday facts were checked against current sources (see below).
A17: Compliance wording | B17: Stockstrail is described as an 'AMFI-registered mutual fund distributor (ARN-284122)'. Review Fix List F6-F8 with a compliance professional.
A19: LIVE QA (formulas)
A20: Main-site pages covered | B20: =COUNTA('Meta - Main Site'!C5:C53) -> 49
A21: Learning pages covered | B21: =COUNTA('Meta - Learning'!C5:C56) -> 52
A22: New titles over 60 characters | B22: =COUNTIF('Meta - Main Site'!F5:F53,">60")+COUNTIF('Meta - Learning'!F5:F56,">60") -> 0
A23: New descriptions over 160 characters | B23: =COUNTIF('Meta - Main Site'!H5:H53,">160")+COUNTIF('Meta - Learning'!H5:H56,">160") -> 0
A24: OLD titles over 60 characters | B24: =COUNTIF('Meta - Main Site'!Q5:Q53,">60")+COUNTIF('Meta - Learning'!Q5:Q56,">60") -> 70
A25: Avg. new title length | B25: =ROUND((SUM('Meta - Main Site'!F5:F53)+SUM('Meta - Learning'!F5:F56))/(COUNT('Meta - Main Site'!F5:F53)+COUNT('Meta - Learning'!F5:F56)),1) -> 54.4
A27: FACTS CHECKED (9 Oct 2026) AND SOURCES
A28: NSE/BSE holidays 2026 | B28: 15 weekday equity trading holidays (Outlook Money, Tata Mutual Fund, Finology). Muhurat Trading is Sunday 8 Nov 2026, confirmed in an NSE circular; timings are announced closer to the date. Remaining 2026 closures after today: 20 Oct, 10 Nov, 24 Nov, 25 Dec.
A29: Income tax FY 2026-27 | B29: Budget 2026 (1 Feb 2026) made no change to slabs; new regime remains default; income up to ₹12 lakh effectively tax-free via the 87A rebate; standard deduction ₹75,000 (new) / ₹50,000 (old). The Income-tax Act 2025 replaces the 1961 Act from 1 Apr 2026 (Tata Capital, BankBazaar, Bajaj Finserv, Basunivesh). Verify section numbering before quoting 87A/80C.
A30: Loan against mutual funds | B30: RBI issued revised LAMF rules on 13 Feb 2026, with a ₹1 crore cap effective July 2026 (Upstox). Market rates broadly 8-13% p.a. (JM Financial, Stable Money, Upstox). Your own pages quote 9% and 9.5%: keep one dated figure.
A31: Google meta guidance | B31: Google Search Central, 'Control your snippets in search results': no length limit; truncated to device width; meta description used only when Google considers it more accurate than page text.
A32: Google and AI search | B32: Google, 'Optimizing your website for generative AI features on Google Search' (15 May 2026), as summarised by Search Engine Journal, Practical Ecommerce and others: Google treats AI Overviews/AI Mode optimisation as SEO, with no additional technical requirements. I read these secondary summaries, not Google's primary page.
A34: LIMITS OF THIS WORK
A35: No keyword-volume tool | B35: I could not access Keyword Planner, Semrush or Search Console, so volumes are not exact. Use the Keyword Map as a prioritised hypothesis and confirm with your own Search Console data.
A36: Pages actually read live | B36: Home, About, Services > Mutual Funds, SIP Calculator and Blog home. Other pages were rewritten from your sheet; confirm each description matches what its page actually says before publishing.
A37: Not verified | B37: robots.txt, XML sitemap, structured data, Core Web Vitals, backlinks, Search Console health.
A38: Not legal advice | B38: Compliance flags (Fix List F6-F8) are for review by a qualified professional.

Sheet Meta - Main Site
A1: Stockstrail: Meta titles & descriptions: main site (stockstrail.in)
A2: Green columns are the NEW values to implement. Title target: 60 characters or fewer, brand included. Description target: about 125-160 characters, with the key point in the first ~120 (mobile truncates sooner). 'Title chars' / 'Desc chars' recalculate if you edit the text. Red/amber = outside range.
A4: # | B4: Group | C4: Page | D4: Canonical URL | E4: NEW Meta Title | F4: Title chars | G4: NEW Meta Description | H4: Desc chars | I4: Primary keyword | J4: Secondary / long-tail keywords | K4: Search intent | L4: Priority | M4: Indexing | N4: Why this change / implementation notes | O4: Current Title (from your sheet) | P4: Current Description (from your sheet) | Q4: Old title chars | R4: Old desc chars
A5: 1 | B5: Core | C5: Home Page | D5: https://www.stockstrail.in | E5: Stockstrail | Financial Planning & Mutual Fund SIP in India | F5: =LEN(E5) -> 59 | G5: Stockstrail (AMFI ARN-284122) guides families and salaried professionals on mutual fund SIPs, term & health insurance, FDs and loans. Book a free strategy call. | H5: =LEN(G5) -> 160 | I5: Stockstrail (brand); financial planning India | J5: mutual fund SIP India; mutual fund distributor Himachal Pradesh; goal based financial planning; AMFI registered distributor | K5: Navigational + Commercial | L5: P1 | M5: index | N5: Dropped 'India's trusted' (unverifiable superlative) and 'Expert advisory' (see compliance fix F7). Home H1 ('Smart Investing for Your Family...') has no primary keyword: suggest 'Financial Planning & Mutual Fund Guidance in India'. Add Organization + FinancialService + WebSite schema with sameAs links. | O5: Stockstrail | Financial Planning & Investment Platform India | P5: Stockstrail (AMFI ARN-284122) is India's trusted financial planning and investment platform. Expert advisory on Mutual Funds SIP, Term Insurance, Fixed Deposits, and Loans. | Q5: =LEN(O5) -> 60 | R5: =LEN(P5) -> 172
A6: 2 | B6: Core | C6: About Us | D6: https://www.stockstrail.in/about | E6: About Stockstrail | Vikrant Bhardwaj, AMFI ARN-284122 | F6: =LEN(E6) -> 53 | G6: Meet Vikrant Bhardwaj, founder of Stockstrail, an AMFI-registered mutual fund distributor (ARN-284122) in Himachal Pradesh serving 200+ clients across India. | H6: =LEN(G6) -> 157 | I6: about Stockstrail; Vikrant Bhardwaj | J6: AMFI registered mutual fund distributor Himachal Pradesh; NISM Series V-A certified distributor | K6: Navigational / Trust (E-E-A-T) | L6: P1 | M6: index | N6: Live site currently serves an OLDER title/description than your sheet ('About Us | Stockstrail — Founder, Certifications & Our Approach'): confirm what is deployed. Put the person + credential in the title: this is the authority page AI systems cite. Remove the 'SEBI Registered' label next to the SEBI exam certificate (exam certification is not registration). Add Person schema + author page. | O6: About Stockstrail | Financial Planning & Investment Guidance in India | P6: Learn about Stockstrail, an AMFI-registered practice founded by Vikrant Bhardwaj (ARN-284122) to make financial planning and investment decisions easier to understand, with goal-focused guidance across India. | Q6: =LEN(O6) -> 69 | R6: =LEN(P6) -> 208
A7: 3 | B7: Core | C7: Services Directory | D7: https://www.stockstrail.in/services | E7: Mutual Funds, Insurance, FD & Loan Services | Stockstrail | F7: =LEN(E7) -> 57 | G7: Explore Stockstrail's services: mutual fund SIPs, term & health insurance, fixed deposits, loan against mutual funds and Demat accounts. AMFI ARN-284122. | H7: =LEN(G7) -> 153 | I7: financial services India | J7: mutual fund services; insurance FD loan services; financial planning services | K7: Commercial / Navigational | L7: P1 | M7: index | N7: Hub page: every service card should link to the canonical /services/... URL (About and Blog footers currently link to non-canonical /mutual-funds, /loan etc.). | O7: Services - Mutual Funds, Insurance, Fixed Deposits & Loans | Stockstrail | P7: Explore our comprehensive financial services including Mutual Funds, Fixed Deposits, Insurance, and Loans. Expert guidance tailored to your needs. | Q7: =LEN(O7) -> 72 | R7: =LEN(P7) -> 146
A8: 4 | B8: Core | C8: Let's Talk (Consultation) | D8: https://www.stockstrail.in/lets-talk | E8: Contact Stockstrail | Book a Free Financial Planning Call | F8: =LEN(E8) -> 57 | G8: Talk to Stockstrail about SIPs, insurance, FDs or loans. Book a free strategy call or message us on WhatsApp, Mon-Sat 9 AM-8 PM IST. No sales pressure. | H8: =LEN(G8) -> 151 | I8: contact Stockstrail; free financial planning call | J8: book financial consultation; Stockstrail phone WhatsApp; financial planner Himachal Pradesh | K8: Navigational / Lead-gen | L8: P1 | M8: index | N8: Navigational 'contact' intent + transactional CTA. Add ContactPage schema; keep name, address (Moien, Chintpurni, HP 177110), phone and hours identical to your Google Business Profile. | O8: Let's Talk - Connect With Stockstrail Financial Experts | P8: Have questions or need assistance? Reach out to Stockstrail's financial experts today for guidance on mutual funds, insurance, and more. | Q8: =LEN(O8) -> 55 | R8: =LEN(P8) -> 136
A9: 5 | B9: Services | C9: Mutual Funds Advisory | D9: https://www.stockstrail.in/services/mutual-funds | E9: Mutual Fund SIP & Lumpsum Investment in India | Stockstrail | F9: =LEN(E9) -> 59 | G9: Start a mutual fund SIP or lumpsum with Stockstrail (AMFI ARN-284122). Compare equity, debt and hybrid funds, check your risk profile and book a free call. | H9: =LEN(G9) -> 155 | I9: mutual fund investment India | J9: SIP and lumpsum investment; equity debt hybrid funds; how to invest in mutual funds; mutual fund distributor | K9: Commercial | L9: P1 | M9: index | N9: LIVE <title> renders 'Stockstrail | Stockstrail' (brand twice): fix the title template (F1). Dropped 'Best' (superlative; AMFI/SEBI advertising code) and 'Advisory'. Page links to the noindex /risk-profile in places: link /check-risk-profile instead. | O9: Mutual Funds India: Best SIP & Lumpsum Investment Advisory | Stockstrail | P9: Start disciplined mutual fund investing with Stockstrail (AMFI ARN-284122). Compare SIP vs lumpsum options, equity and debt fund categories, and get personalized wealth guidance. | Q9: =LEN(O9) -> 72 | R9: =LEN(P9) -> 178
A10: 6 | B10: Services | C10: Insurance Planning | D10: https://www.stockstrail.in/services/insurance | E10: Compare Term & Health Insurance in India | Stockstrail | F10: =LEN(E10) -> 54 | G10: Compare term life and health insurance in India: claim settlement ratio, cover amount, cashless hospitals and riders. Get a free policy review from Stockstrail. | H10: =LEN(G10) -> 160 | I10: term insurance India | J10: health insurance comparison; term vs health insurance; claim settlement ratio; critical illness rider | K10: Commercial / Comparison | L10: P1 | M10: index | N10: Removed '99%+ claim settlement' from meta: the figure varies by insurer and year; use it only if the page cites IRDAI data. Your AMFI ARN does not cover insurance: show your IRDAI licence / POSP / agency disclosure on this page (F8). | O10: Term & Health Insurance in India: Plans & Comparison | Stockstrail | P10: Protect your family with top Term Life and Health Insurance plans in India. Compare 99%+ claim settlement ratios, cashless network hospitals, critical illness riders, and get expert advisory from Stockstrail. | Q10: =LEN(O10) -> 66 | R10: =LEN(P10) -> 208
A11: 7 | B11: Services | C11: Fixed Deposits | D11: https://www.stockstrail.in/services/fixed-deposit | E11: Fixed Deposit Guide 2026: Types, Rates & Tax | Stockstrail | F11: =LEN(E11) -> 58 | G11: Understand fixed deposits in India: bank vs corporate FDs, senior citizen rates, TDS, tax rules and FD laddering. Calculate returns, then talk to Stockstrail. | H11: =LEN(G11) -> 158 | I11: fixed deposit guide | J11: FD interest rates 2026; bank FD vs corporate FD; senior citizen FD; FD tax TDS; FD laddering | K11: Informational + Commercial | L11: P1 | M11: index | N11: Year in title lifts CTR on rate queries: refresh every January. Rate claims differ across your pages (About: 'up to 7.5%'; SIP page: 'up to 9.1%'): make one dated, sourced figure (F12). | O11: Fixed Deposit (FD) Guide 2026: Types, Interest Rates & Tax Rules | Stockstrail | P11: Complete guide to Fixed Deposits in India. Explore types of fixed deposits, Bank vs Corporate FD interest rates, senior citizen benefits, tax rules, and calculation. | Q11: =LEN(O11) -> 78 | R11: =LEN(P11) -> 165
A12: 8 | B12: Services | C12: Loan Against Mutual Funds (LAMF) | D12: https://www.stockstrail.in/services/loan | E12: Loan Against Mutual Funds (LAMF) Rates & Apply | Stockstrail | F12: =LEN(E12) -> 60 | G12: Borrow against your mutual funds without selling them. Check LAMF interest rates, loan-to-value, eligibility and how to apply with Stockstrail (ARN-284122). | H12: =LEN(G12) -> 156 | I12: loan against mutual funds | J12: LAMF interest rate; loan against mutual funds eligibility; LAMF vs personal loan; how to apply | K12: Commercial | L12: P1 | M12: index | N12: Timely: RBI issued new LAMF rules on 13 Feb 2026 (₹1 crore cap effective July 2026): add a 'What changed in 2026' section. Meta avoids a fixed rate: market range is roughly 8-13% p.a. and your pages quote 9% (meta) and 9.5% (SIP page). | O12: Loan Against Mutual Funds (LAMF) & Business Loans in India | Stockstrail | P12: Get instant Loan Against Mutual Funds (LAMF) without selling your investments. Compare low interest rates starting from 9%, zero foreclosure charges, and quick approval with Stockstrail. | Q12: =LEN(O12) -> 72 | R12: =LEN(P12) -> 186
A13: 9 | B13: Services | C13: Financial Protection | D13: https://www.stockstrail.in/services/financial-protection | E13: Financial Protection Planning for Families | Stockstrail | F13: =LEN(E13) -> 56 | G13: Build a family safety net: term and health insurance, emergency fund, motor and travel cover and tax-filing support. Start with a free Stockstrail review. | H13: =LEN(G13) -> 154 | I13: financial protection plan | J13: family financial protection; emergency fund planning; motor insurance; travel insurance; tax filing support | K13: Informational + Commercial | L13: P2 | M13: index | N13: Overlaps with /services/insurance. Keep this as the umbrella page (emergency fund, motor/travel, tax filing) and cross-link both ways to avoid cannibalisation. | O13: Financial Protection & Insurance Planning | Stockstrail | P13: Understand and plan your financial protection with Stockstrail. Explore insurance, emergency savings, motor and travel insurance, tax filing support and financial solutions based on your needs. | Q13: =LEN(O13) -> 55 | R13: =LEN(P13) -> 193
A14: 10 | B14: Services | C14: Open Demat Account | D14: https://www.stockstrail.in/services/open-demat | E14: Open Demat & Trading Account Online in India | Stockstrail | F14: =LEN(E14) -> 58 | G14: Open a paperless Demat and trading account online with leading brokers. Learn the KYC steps, documents and charges, then get step-by-step help from Stockstrail. | H14: =LEN(G14) -> 160 | I14: open demat account online | J14: demat account documents; demat account charges; zero AMC demat account; trading account opening | K14: Commercial / Transactional | L14: P2 | M14: index | N14: 'Open demat account' head term is owned by brokers (Zerodha, Groww, Angel One): win with specifics (documents, charges, NRI/minor accounts, Himachal). Drop 'India's top brokers' (superlative). Disclose your partner/referral status with each broker (F8). | O14: Open Demat Account - Start Stock Market Investing | Stockstrail | P14: Open a free Demat account with Stockstrail. Trade stocks, mutual funds, IPOs, and more with India's top brokers. Zero account opening charges, seamless KYC, and expert guidance. | Q14: =LEN(O14) -> 63 | R14: =LEN(P14) -> 177
A15: 11 | B15: Calculators | C15: Calculators Hub | D15: https://www.stockstrail.in/calculators | E15: Free Financial Calculators: SIP, FD, EMI & Tax | Stockstrail | F15: =LEN(E15) -> 60 | G15: Use Stockstrail's free calculators for SIP, lumpsum, FD, RD, loan EMI and income tax FY 2026-27. Instant results, no login. Plan goals with realistic numbers. | H15: =LEN(G15) -> 158 | I15: financial calculators India | J15: SIP lumpsum FD RD EMI tax calculator; free investment calculators | K15: Tool / Navigational | L15: P1 | M15: index | N15: Removed 'institutional-grade' (unverifiable). Roadmap: SWP, PPF, NPS, retirement, goal and CAGR calculators are high-demand gaps (see Keyword Map). | O15: Financial Calculators - SIP, Lumpsum, FD, RD, EMI & Tax | Stockstrail | P15: Free institutional-grade financial calculators for Indian investors. Calculate Mutual Fund SIP returns, Lumpsum wealth, Fixed Deposit interest, RD maturity, Loan EMI, and Income Tax liability. | Q15: =LEN(O15) -> 69 | R15: =LEN(P15) -> 192
A16: 12 | B16: Calculators | C16: SIP Calculator | D16: https://www.stockstrail.in/calculators/sip | E16: SIP Calculator with Step-Up: Estimate Returns | Stockstrail | F16: =LEN(E16) -> 59 | G16: Free SIP calculator with step-up option. See how a monthly mutual fund SIP could grow with compounding, view the year-wise schedule and plan goals. No login. | H16: =LEN(G16) -> 157 | I16: SIP calculator | J16: step up SIP calculator; SIP return calculator; mutual fund SIP calculator; SIP calculator with inflation | K16: Tool | L16: P1 | M16: index | N16: LIVE <title> duplicates the brand ('| Stockstrail | Stockstrail'). Your page already has Step-Up, so 'step up SIP calculator' (strong mid-tail) is a legitimate target. Add an inflation-adjusted toggle to also capture 'SIP calculator with inflation'. Add WebApplication schema and an 'estimates, not guaranteed' note. 'SIP calculator' head term is dominated by Groww/ET Money/AMCs: win the long-tail first. | O16: SIP Calculator - Calculate Mutual Fund SIP Returns Online | Stockstrail | P16: Estimate your Systematic Investment Plan (SIP) returns with Stockstrail's free SIP calculator. Plan your wealth creation with accurate compound interest projections. | Q16: =LEN(O16) -> 71 | R16: =LEN(P16) -> 165
... A53: 49 | B53: Account & Admin | C53: Admin Dashboard | D53: https://www.stockstrail.in/admin/dashboard | E53: Admin Dashboard | Stockstrail | F53: =LEN(E53) -> 29 | G53: Admin panel for managing risk profiles. | H53: =LEN(G53) -> 39 | I53: - | J53: - | K53: Admin | L53: P3 | M53: NOINDEX | N53: Already noindex. No change needed. | O53: Admin Dashboard | Stockstrail | P53: Admin panel for managing risk profiles | Q53: =LEN(O53) -> 29 | R53: =LEN(P53) -> 38

Sheet Meta - Learning
A1: Stockstrail Learning: Meta titles & descriptions (learning.stockstrail.in)
A2: Same rules as the main-site sheet. Lesson titles now lead with the search query instead of a label, and the 'Stockstrail' brand closes each title.
A4: # | B4: Group | C4: Page | D4: Canonical URL | E4: NEW Meta Title | F4: Title chars | G4: NEW Meta Description | H4: Desc chars | I4: Primary keyword | J4: Secondary / long-tail keywords | K4: Search intent | L4: Priority | M4: Indexing | N4: Why this change / implementation notes | O4: Current Title (from your sheet) | P4: Current Description (from your sheet) | Q4: Old title chars | R4: Old desc chars
A5: 1 | B5: Learning Hub | C5: Learning Home | D5: https://learning.stockstrail.in | E5: Stockstrail Learning: Free Investing & Finance Courses India | F5: =LEN(E5) -> 60 | G5: Free, structured courses on mutual funds, SIP, insurance, tax saving, stock market and retirement for Indian investors. No login, no ads, no sales pitch. | H5: =LEN(G5) -> 153 | I5: free finance courses India | J5: learn mutual funds free; investing course for beginners; personal finance course India | K5: Informational / Hub | L5: P1 | M5: index | N5: Remove 'SEBI-aware' (vague). Home must link to every course with descriptive anchors. Add Organization schema (publisher = Stockstrail) so the subdomain inherits brand entity; consider moving under stockstrail.in/learn long-term (F21). | O5: Stockstrail Learning — Free Investing & Personal Finance Courses for India | P5: Free structured courses on mutual funds, SIP, insurance, tax saving, stock market, and retirement planning — built for Indian investors. No login, no ads, SEBI-aware content. | Q5: =LEN(O5) -> 74 | R5: =LEN(P5) -> 174
A6: 2 | B6: Learning Hub | C6: About Learning Hub | D6: https://learning.stockstrail.in/about | E6: About Stockstrail Learning | Free Finance Education India | F6: =LEN(E6) -> 57 | G6: Stockstrail Learning is a free finance education hub for Indian investors: mutual funds, SIPs, tax saving and risk profiling without jargon or sales pitches. | H6: =LEN(G6) -> 157 | I6: Stockstrail Learning | J6: free financial education India; who runs Stockstrail Learning | K6: Navigational / Trust | L6: P3 | M6: index | N6: Name the author/reviewer (Vikrant Bhardwaj, ARN-284122, NISM V-A) on this page: it is the trust page for the subdomain. | O6: About Stockstrail Learning — Free Financial Education Hub for Indian Investors | P6: Discover Stockstrail Learning — a 100% free, structured financial education hub for Indian retail investors. Learn about Mutual Funds, SIPs, Tax Saving, Risk Profiling, and Personal Finance without jargon or sales pitches. | Q6: =LEN(O6) -> 78 | R6: =LEN(P6) -> 222
A7: 3 | B7: Learning Hub | C7: Categories Directory | D7: https://learning.stockstrail.in/categories | E7: Finance Topics & Courses: Browse All | Stockstrail Learning | F7: =LEN(E7) -> 59 | G7: Browse finance topics on Stockstrail Learning: mutual funds, SIP, insurance, stock market, demat, tax saving, loans, retirement and financial planning. | H7: =LEN(G7) -> 151 | I7: finance topics to learn | J7: personal finance topics; investing categories | K7: Navigational | L7: P3 | M7: index | N7: Old title/description were too thin to rank or earn clicks. | O7: Categories — Stockstrail Learning | P7: Browse finance topics — mutual funds, SIP, insurance, stocks, tax, retirement and more. | Q7: =LEN(O7) -> 33 | R7: =LEN(P7) -> 87
A8: 4 | B8: Learning Hub | C8: Courses Directory | D8: https://learning.stockstrail.in/courses | E8: All Free Finance Courses in India | Stockstrail Learning | F8: =LEN(E8) -> 56 | G8: Browse all 12 free finance courses: mutual funds, SIP, insurance, tax saving, retirement and more. Filter by difficulty, category and reading time. | H8: =LEN(G8) -> 147 | I8: free finance courses | J8: online investing courses India; beginner finance course; free mutual fund course | K8: Navigational / Informational | L8: P2 | M8: index | N8: '12' must be kept in sync with the catalogue: render it from the database (avoid hard-coding). | O8: All Courses — Stockstrail Learning | P8: Browse every finance course on Stockstrail Learning. Filter by difficulty, category and reading time. | Q8: =LEN(O8) -> 34 | R8: =LEN(P8) -> 101
A9: 5 | B9: Learning Category | C9: personal-finance-basics | D9: https://learning.stockstrail.in/categories/personal-finance-basics | E9: Personal Finance Basics: Free Courses | Stockstrail | F9: =LEN(E9) -> 51 | G9: Learn to manage daily money, budget well, get out of debt and choose the right insurance for your family with free personal finance basics courses. | H9: =LEN(G9) -> 147 | I9: personal finance basics | J9: budgeting course; get out of debt; insurance basics | K9: Informational / Hub | L9: P3 | M9: index | N9: DUPLICATE of /categories/personal-finance (near-identical topic). Merge into one category and 301 the other (F10). | O9: Personal Finance Basics Courses — Stockstrail Learning | P9: Learn how to manage your daily money, budget effectively, get out of debt, and buy the right insurance protection for you and your family. | Q9: =LEN(O9) -> 54 | R9: =LEN(P9) -> 138
A10: 6 | B10: Learning Category | C10: mutual-funds | D10: https://learning.stockstrail.in/categories/mutual-funds | E10: Mutual Fund Courses for Beginners (Free) | Stockstrail | F10: =LEN(E10) -> 54 | G10: Free mutual fund courses and lessons: what mutual funds are, NAV, expense ratios, direct vs regular plans, SIP vs lumpsum and taxation. | H10: =LEN(G10) -> 135 | I10: mutual fund course | J10: learn mutual funds; mutual funds for beginners; NAV expense ratio | K10: Informational / Hub | L10: P2 | M10: index | N10: Old title/description were thin: now topic-specific and benefit-led. | O10: Mutual Funds Courses — Stockstrail Learning | P10: Pooled investments, NAV, expense ratios and more. | Q10: =LEN(O10) -> 43 | R10: =LEN(P10) -> 49
A11: 7 | B11: Learning Category | C11: sip | D11: https://learning.stockstrail.in/categories/sip | E11: SIP Courses: Learn Systematic Investing | Stockstrail | F11: =LEN(E11) -> 53 | G11: Learn how SIPs work with free lessons on rupee cost averaging, step-up SIPs, compounding and common SIP myths for Indian investors. | H11: =LEN(G11) -> 131 | I11: SIP course | J11: learn SIP; systematic investment plan basics | K11: Informational / Hub | L11: P2 | M11: index | N11: Old title/description were thin: now topic-specific and benefit-led. | O11: SIP Courses — Stockstrail Learning | P11: Systematic Investment Plans and disciplined investing. | Q11: =LEN(O11) -> 34 | R11: =LEN(P11) -> 54
A12: 8 | B12: Learning Category | C12: swp | D12: https://learning.stockstrail.in/categories/swp | E12: SWP Courses: Systematic Withdrawal Plans | Stockstrail | F12: =LEN(E12) -> 54 | G12: Learn how a Systematic Withdrawal Plan (SWP) can create regular income from your mutual fund investments, and when it makes sense. | H12: =LEN(G12) -> 130 | I12: SWP mutual fund | J12: systematic withdrawal plan; SWP vs SIP; SWP for retirement income | K12: Informational / Hub | L12: P3 | M12: NOINDEX | N12: No course currently sits in this category (thin page): set noindex until an SWP course exists. SWP calculator + course is a good high-demand pair. | O12: SWP Courses — Stockstrail Learning | P12: Systematic Withdrawal Plans for cashflow. | Q12: =LEN(O12) -> 34 | R12: =LEN(P12) -> 41
A13: 9 | B13: Learning Category | C13: insurance | D13: https://learning.stockstrail.in/categories/insurance | E13: Insurance Courses: Term, Health & More | Stockstrail | F13: =LEN(E13) -> 52 | G13: Free insurance courses for Indian families: term vs traditional plans, health insurance riders, claim settlement ratios and how much cover you need. | H13: =LEN(G13) -> 148 | I13: insurance course | J13: learn term insurance; health insurance basics; claim settlement ratio | K13: Informational / Hub | L13: P2 | M13: index | N13: Old title/description were thin: now topic-specific and benefit-led. | O13: Insurance Courses — Stockstrail Learning | P13: Protect your family and your wealth. | Q13: =LEN(O13) -> 40 | R13: =LEN(P13) -> 36
A14: 10 | B14: Learning Category | C14: stock-market | D14: https://learning.stockstrail.in/categories/stock-market | E14: Stock Market Courses for Beginners | Stockstrail | F14: =LEN(E14) -> 48 | G14: Learn how the stock market works with free beginner courses on shares, Sensex and Nifty, market cycles and long-term investing. | H14: =LEN(G14) -> 127 | I14: stock market course | J14: stock market for beginners; Sensex Nifty basics | K14: Informational / Hub | L14: P2 | M14: index | N14: Old title/description were thin: now topic-specific and benefit-led. | O14: Stock Market Courses — Stockstrail Learning | P14: Equities, indices, and how markets work. | Q14: =LEN(O14) -> 43 | R14: =LEN(P14) -> 40
A15: 11 | B15: Learning Category | C15: demat | D15: https://learning.stockstrail.in/categories/demat | E15: Demat Account Courses: Open & Use Safely | Stockstrail | F15: =LEN(E15) -> 54 | G15: Free lessons on how to open, use and secure a Demat and trading account in India, with NSDL and CDSL depositories explained in simple steps. | H15: =LEN(G15) -> 140 | I15: demat account guide | J15: how to open demat account; NSDL CDSL | K15: Informational / Hub | L15: P3 | M15: index | N15: Old title/description were thin: now topic-specific and benefit-led. | O15: Demat Accounts Courses — Stockstrail Learning | P15: Open, use and secure a demat account. | Q15: =LEN(O15) -> 45 | R15: =LEN(P15) -> 37
A16: 12 | B16: Learning Category | C16: personal-finance | D16: https://learning.stockstrail.in/categories/personal-finance | E16: Personal Finance Courses: Budgeting & Saving | Stockstrail | F16: =LEN(E16) -> 58 | G16: Free personal finance courses on budgeting, saving and healthy money habits, including the 50/30/20 rule and emergency funds. | H16: =LEN(G16) -> 125 | I16: personal finance course | J16: budgeting course; money habits; 50/30/20 rule | K16: Informational / Hub | L16: P3 | M16: index | N16: Merge with personal-finance-basics (see above) and keep this as the single canonical category. | O16: Personal Finance Courses — Stockstrail Learning | P16: Budgeting, saving, and money habits. | Q16: =LEN(O16) -> 47 | R16: =LEN(P16) -> 36
... A56: 52 | B56: Learning Lesson | C56: loans-decoded / how-emi-splits | D56: https://learning.stockstrail.in/courses/loans-decoded/how-emi-splits | E56: How EMI Works: Interest vs Principal Split | Stockstrail | F56: =LEN(E56) -> 56 | G56: In the early years of a loan, most of each EMI goes to interest, not principal. Learn how an EMI splits over time and why prepayment helps. | H56: =LEN(G56) -> 139 | I56: how EMI is calculated | J56: EMI interest and principal split; loan amortization; prepayment | K56: Informational | L56: P3 | M56: index | N56: Old title (~90 chars) was truncated and led with a label, not the query. Add a link back to the parent course, next/previous lesson and a 'Try the calculator' CTA. | O56: How EMI Splits — Loans & Credit: Borrow Smart, Repay Faster | Stockstrail Learning | P56: In the early years of a loan, most of your EMI goes toward interest rather than principal reduction. | Q56: =LEN(O56) -> 82 | R56: =LEN(P56) -> 100

Sheet Keyword Map
A1: Keyword map: where each target keyword should live
A2: IMPORTANT: Demand and competition are directional estimates from the search results I could see (who ranks) and normal Indian search behaviour. I did not have Google Keyword Planner, Semrush or Search Console data, so there are no exact monthly volumes. Validate in Search Console (your own impressions) and Keyword Planner before committing effort. 'Winnability' = realistic chance for a small, new site: Quick win / Good / Long game / Defend.
A4: Cluster | B4: Target keyword | C4: Search intent | D4: Est. demand (India) | E4: Est. competition | F4: Winnability | G4: Target page | H4: Action
A5: Brand | B5: Stockstrail | C5: Navigational | D5: Low | E5: Low | F5: Defend | G5: Home, About, GBP, LinkedIn | H5: Own the whole first page: Home, About, learning subdomain, Google Business Profile, LinkedIn, Facebook, Instagram, Telegram and any AMFI/directory listing, all with identical name + ARN.
A6: Brand | B6: Vikrant Bhardwaj Stockstrail / ARN-284122 | C6: Navigational | D6: Low | E6: Low | F6: Defend | G6: About | H6: Person schema + a dedicated author page listing credentials; reuse the same bio everywhere.
A7: Local | B7: mutual fund distributor in Himachal Pradesh | C7: Local commercial | D7: Low | E7: Low | F7: Quick win | G7: NEW: /financial-planning-himachal-pradesh (+ Home) | H7: One strong hub with unique local content (govt-employee scenarios, district notes, your Chintpurni office, local reviews). Avoid 12 near-identical district blocks/pages.
A8: Local | B8: financial planner Himachal Pradesh / Una / Kangra / Dharamshala / Shimla | C8: Local commercial | D8: Low | E8: Low | F8: Quick win | G8: Same hub + short city sections | H8: Confirm 'advisor/planner' wording with compliance first (Fix List F7).
A9: Local | B9: mutual fund distributor near me / Chintpurni | C9: Local | D9: Medium | E9: Low | F9: Quick win | G9: Google Business Profile + About | H9: Complete the GBP (closest category, photos, hours, services, Q&A), collect real reviews, keep NAP identical to the site.
A10: Mutual funds | B10: mutual fund investment India | C10: Commercial | D10: High | E10: High | F10: Long game | G10: /services/mutual-funds | H10: Support with the beginner pillar + internal links from every chapter.
A11: Mutual funds | B11: how to invest in mutual funds | C11: Informational | D11: Very High | E11: Very High | F11: Long game | G11: Blog #12 | H11: Flagship of the pillar page; numbered steps; answer-first intro; strong CTA to /services/mutual-funds.
A12: Mutual funds | B12: types of mutual funds | C12: Informational | D12: High | E12: High | F12: Good | G12: Blog #5 (+ learning lesson) | H12: Fix the raw-slug title now; add a comparison table of categories.
A13: Mutual funds | B13: SIP vs lumpsum | C13: Informational / comparison | D13: High | E13: High | F13: Good | G13: Blog #16 (lesson links to it) | H13: Add a comparison table and embed both calculators.
A14: Mutual funds | B14: direct vs regular mutual fund | C14: Informational / comparison | D14: High | E14: High | F14: Good | G14: Learning lesson + blog FAQ | H14: Your edge is honesty: explain the commission difference openly (trust + E-E-A-T).
A15: Mutual funds | B15: mutual fund taxation 2026 / LTCG STCG | C15: Informational | D15: High | E15: High | F15: Good | G15: Blog #14 | H15: Date-stamp and cite the Income Tax Department / Finance Act; refresh after every Budget.
... A45: Demat | B45: open demat account online | C45: Transactional | D45: Very High | E45: Very High | F45: Long game | G45: /services/open-demat | H45: Target long-tails: documents required, demat charges, zero AMC, NRI/minor accounts.

Sheet Fix List
A1: Fix list: issues found on the live site, in priority order
A2: IDs (F1, F7 ...) are referenced from the notes on the Meta sheets. P1 = do first. Compliance items are flags for review by a qualified professional, not legal advice.
A4: ID | B4: Priority | C4: Area | D4: Issue | E4: Where / evidence | F4: Recommended fix | G4: Owner
A5: F1 | B5: P1 | C5: Title tags | D5: Brand name appears twice in the rendered <title> on many pages. | E5: Live pages: /services/mutual-funds, /blog, /calculators/sip all end '| Stockstrail | Stockstrail'. Home and About render correctly. | F5: Use a title template ('%s | Stockstrail') and remove '| Stockstrail' from per-page titles, or set an absolute title on pages that already contain the brand. | G5: Developer
A6: F2 | B6: P1 | C6: Deployment | D6: Your sheet and the live site disagree on some metadata. | E6: About live title: 'About Us | Stockstrail — Founder, Certifications & Our Approach'; Blog live title: 'Financial Insights & Investment Strategies Blog | Stockstrail | Stockstrail'. Your sheet lists different values. | F6: Confirm which version is deployed, purge CDN/ISR cache, then treat the final sheet as the single source of truth. | G6: Developer
A7: F3 | B7: P1 | C7: Indexing | D7: Gated pages are indexable and carry the home-page description. | E7: /sign-in and /complete-profile are 'index, follow' with inherited root meta (your sheet). | F7: Set robots to noindex,nofollow and remove both from the XML sitemap. | G7: Developer
A8: F4 | B8: P1 | C8: Title tags | D8: A blog post title is a raw slug. | E8: Blog #5: 'Stockstrail-Mutual-Funds-Chapter-4 | Stockstrail'. | F8: Replace with the new title (see Meta - Main Site). | G8: Content
A9: F5 | B9: P1 | C9: Content freshness | D9: Time-bound article now reads as out of date. | E9: Blog #18 says 'Before September 1' but today is 9 Oct 2026. | F9: Rewrite as a 'how to add a nominee now' guide, re-verify against the SEBI circular, add 'Last updated'. | G9: Content
A10: F6 | B10: P1 | C10: Compliance / trust | D10: Fee and commission claims contradict your own disclosure. | E10: SIP calculator page: '100% Free Advice', 'zero distributor markups', 'Direct AMC Execution', 'zero advisory fees', 'Zero-commission direct AMC investment', footer 'unbiased advice'. Home disclosure: 'we receive commissions from AMCs'. MF page FAQ: Regular plans include distribution expenses. | F10: Make every page consistent with the commission disclosure. Remove absolute claims ('zero', 'unbiased', 'top-performing'). Have a compliance professional review. | G10: Founder + compliance
A11: F7 | B11: P1 | C11: Compliance / trust | D11: Titles such as 'advisor', 'SEBI-certified' and a 'SEBI Registered' label may mislead. | E11: About page: label 'SEBI Registered' beside a SEBI Investor Certification exam certificate; 'SEBI-Certified Advisor'; footer 'Founder & Principal Advisor'; 'certified financial advisor'. | F11: You are an AMFI-registered mutual fund distributor (ARN-284122). An exam certificate is not SEBI registration. Use 'AMFI-registered mutual fund distributor' and have compliance confirm whether 'advisor/advisory' wording is acceptable. I am not a lawyer; please verify. | G11: Founder + compliance
A12: F8 | B12: P1 | C12: Regulatory disclosures | D12: Disclosures for insurance, loans and Demat were not visible on the pages I read. | E12: Pages I read show only AMFI / NISM / SEBI-exam credentials. An AMFI ARN does not cover insurance distribution, loan sourcing or broker referrals. | F12: On each of those service pages show the relevant licence / partner status (for example IRDAI licence or POSP details, lending partners, broker partner relationship) next to the CTA. | G12: Founder + compliance
A13: F9 | B13: P2 | C13: Internal links | D13: Footers/body links point to non-canonical or noindex URLs. | E13: About links: /mutual-funds, /fixed-deposit, /insurance, /loan, /risk-profile. Blog footer: /mutual-funds, /fixed-deposit, /insurance, /loan, /open-demat, /financial-protection, /learning. MF page links /risk-profile (noindex). About/Blog 'Learn' link uses www.learning.stockstrail.in. | F13: Link straight to canonicals: /services/..., /check-risk-profile, https://learning.stockstrail.in. Avoid relying on redirects. | G13: Developer
A14: F10 | B14: P2 | C14: Duplicate topics | D14: Two near-identical learning categories. | E14: /categories/personal-finance-basics and /categories/personal-finance. | F14: Merge into one category and 301 the other. | G14: Content
A15: F11 | B15: P2 | C15: Thin pages | D15: Empty category page. | E15: /categories/swp has no matching course. | F15: noindex until an SWP course exists (then build an SWP calculator too). | G15: Content
... A28: F24 | B28: P3 | C28: Content roadmap | D28: High-demand calculator and comparison gaps. | E28: See Keyword Map: SWP, PPF, NPS, retirement, CAGR calculators; FD vs SIP; LAMF vs personal loan. | F28: Add in the order shown in the Keyword Map. | G28: Content

Sheet AEO-GEO Playbook
A1: AEO / GEO playbook: being the source AI answers and Google quote
A2: Google states that optimising for AI Overviews and AI Mode is still SEO, so most of this is about being clear, consistent, fresh and trustworthy.
A4: # | B4: Lever | C4: What to do | D4: Where on Stockstrail | E4: Why it matters
A5: 1 | B5: Treat AEO/GEO as SEO | C5: Google's guide 'Optimizing your website for generative AI features on Google Search' (15 May 2026) treats AI Overviews/AI Mode as ordinary SEO: same index, no extra files or special markup required for Google. | D5: Whole site | E5: Prioritise crawlable, indexable, genuinely helpful pages over 'AI tricks'.
A6: 2 | B6: Answer-first writing | C6: Under every question heading put a direct 40-60 word answer first, then the detail, table or example. | D6: FAQs, blog posts, learning lessons | E6: AI Overviews and snippets lift concise, self-contained answers.
A7: 3 | B7: Cover the whole query fan-out | C7: For each pillar, answer the sub-questions people ask next: cost, eligibility, tax, risks, alternatives, how to start. | D7: LAMF, FD, MF, insurance pages | E7: Generative search expands one query into many sub-queries; broad coverage gives more chances to be cited.
A8: 4 | B8: Use tables and lists for comparisons | C8: Direct vs Regular, Term vs ULIP, FD vs RD vs SIP, Old vs New tax regime as simple HTML tables. | D8: Blog + learning | E8: Structured comparisons are easy to quote.
A9: 5 | B9: Make entity facts identical everywhere | C9: Name, ARN-284122, founder, address, phone, hours, services and counts (AMCs, clients) must match across site, Google Business Profile, LinkedIn, Facebook, Instagram and directories. Use sameAs in schema. | D9: Sitewide | E9: Consistent facts help search and AI systems resolve who you are.
A10: 6 | B10: Show real expertise and sources | C10: Named author/reviewer with credentials, 'Last reviewed' date, and links to primary sources (SEBI, AMFI, RBI, NSE, IRDAI, Income Tax Dept). | D10: Every article | E10: Financial content is YMYL: trust signals matter more.
A11: 7 | B11: Publish original value | C11: Your calculators, Himachal income-based SIP tables and plain-English explainers are the 'unique point of view' Google asks for. Add more local/data-driven pieces. | D11: Calculators, blog | E11: Generic rewrites of what Groww/ET Money say will not be cited.
A12: 8 | B12: Keep facts fresh | C12: Put the year and a last-updated date on tax, FD, LAMF and holiday pages; update after each Budget, RBI or SEBI change. | D12: Tax, FD, LAMF, NSE/BSE | E12: Stale answers (for example the SEBI nomination post) lose trust and clicks.
A13: 9 | B13: Structured data that matches the page | C13: Organization/FinancialService, WebSite, BreadcrumbList, BlogPosting, Person, WebApplication (calculators), Course. Keep markup consistent with visible content. | D13: Sitewide | E13: Helps understanding; not a ranking guarantee.
A14: 10 | B14: FAQ markup: optional | C14: Since 2023 Google shows FAQ rich results only for a few authoritative government and health sites. Keep visible FAQs for users and AI readers, but do not expect a rich result from FAQPage markup. | D14: FAQs | E14: Avoid wasted effort.
A15: 11 | B15: Earn real mentions | C15: Genuine third-party listings and mentions (AMFI/advisor directories, local news, LinkedIn articles, helpful answers on forums). Google warns that seeking inauthentic mentions can be treated as spam. | D15: Off-site | E15: Corroboration across sources builds authority.
... A17: 13 | B17: Measure it | C17: Track queries/impressions in Search Console and Bing Webmaster Tools; monthly, test 10-15 real customer prompts (for example 'how much SIP should I start in Himachal Pradesh') and log whether Stockstrail is cited. | D17: Process | E17: Turns AEO/GEO into a feedback loop.
